{
  "name": "Industriautomation",
  "icon": "⚙️",
  "version": "1.0",
  "categories": [
    {
      "name": "Cylindrar",
      "color": "#2563eb",
      "icon": "🔩"
    },
    {
      "name": "Ventiler",
      "color": "#7c3aed",
      "icon": "🔧"
    },
    {
      "name": "Gripdon",
      "color": "#059669",
      "icon": "🦾"
    },
    {
      "name": "Sensorer",
      "color": "#d97706",
      "icon": "📡"
    },
    {
      "name": "Styrsystem",
      "color": "#dc2626",
      "icon": "🖥️"
    },
    {
      "name": "Beräkningar",
      "color": "#0891b2",
      "icon": "🧮"
    }
  ],
  "quiz": [
    {
      "c": "Cylindrar",
      "q": "Vad kallas den kraft som kolvstången i en cylinder utvecklar?",
      "o": [
        "Friktionskraft",
        "Aktionskraft",
        "Tryckkraft",
        "Dragkraft"
      ],
      "a": 1,
      "e": "Aktionskraften är den kraft kolvstången utvecklar – den håller fast arbetsstycket, driver matningsrörelse m.m."
    },
    {
      "c": "Cylindrar",
      "q": "Hur beräknas den teoretiska aktionskraften för en cylinder?",
      "o": [
        "F = p / A",
        "F = p × A",
        "F = A / p",
        "F = p + A"
      ],
      "a": 1,
      "e": "F_teor = p × A, dvs. arbetstrycket (p) multiplicerat med kolvarean (A)."
    },
    {
      "c": "Cylindrar",
      "q": "Varför är den verkliga cylinderkraften mindre än den teoretiska?",
      "o": [
        "Trycket är för högt",
        "Friktions- och accelerationskrafter minskar kraften",
        "Kolven är för liten",
        "Cylindern är fel monterad"
      ],
      "a": 1,
      "e": "Friktionskrafter (≈5%) och accelerationskrafter (≈25%) drar av från den teoretiska kraften. F_verk = p × A × (1−0,3)."
    },
    {
      "c": "Cylindrar",
      "q": "Till hur många procent uppskattas friktionskrafterna i en cylinder?",
      "o": [
        "1%",
        "5%",
        "10%",
        "25%"
      ],
      "a": 1,
      "e": "Friktionskrafterna uppskattas till 5% av den teoretiska kraften."
    },
    {
      "c": "Cylindrar",
      "q": "Till hur många procent uppskattas accelerationskrafterna i en cylinder?",
      "o": [
        "5%",
        "10%",
        "15%",
        "25%"
      ],
      "a": 3,
      "e": "Accelerationskrafterna uppskattas till 25% av den teoretiska kraften."
    },
    {
      "c": "Cylindrar",
      "q": "Vad är skillnaden i aktionskraft mellan tryck- och dragriktningen på en dubbelverkande cylinder?",
      "o": [
        "Ingen skillnad",
        "Tryckkraften är större eftersom kolvstången minskar arean på dragsidan",
        "Dragkraften är alltid större",
        "De beror på cylinderlängden"
      ],
      "a": 1,
      "e": "A₁ (trycksida) > A₂ (dragsida) eftersom kolvstångens area räknas bort på dragsidan, vilket ger lägre dragkraft."
    },
    {
      "c": "Cylindrar",
      "q": "Vad är en skyttelcylinder?",
      "o": [
        "En cylinder med dubbelkolv",
        "En enkel cylinder utan kolvstång",
        "En cylinder med genomgående kolvstång som används för skyttelrörelse",
        "En roterande cylinder"
      ],
      "a": 2,
      "e": "En skyttelcylinder har genomgående kolvstång och saknar traditionell kolvstångsstyrning. Aktionskraften är lika i båda riktningarna. Används för korta snabba rörelser."
    },
    {
      "c": "Cylindrar",
      "q": "Vad är en linjärmodul?",
      "o": [
        "En cylinder med fjäderåtergång",
        "En konstruktion av två sammanbyggda cylindrar för stora tvärkrafter",
        "En sensor för linjär rörelse",
        "En ventil för linjärt flöde"
      ],
      "a": 1,
      "e": "Linjärmodulen är uppbyggd av två sammanbyggda cylindrar (dubbla kolvar) och tål stora tvärkrafter i kompakt format."
    },
    {
      "c": "Cylindrar",
      "q": "Vilka är de vanligaste fästena för en pneumatisk cylinder?",
      "o": [
        "Bultar och muttrar",
        "Gavelfäste och fotfäste",
        "Klämbyglar och svetsning",
        "Pinnbult och sprint"
      ],
      "a": 1,
      "e": "Vanliga cylinderfästen är gavelfäste (ändmontage) och fotfäste (sidomontage). På cylindern ska också magnetkolvsavkännare monteras."
    },
    {
      "c": "Cylindrar",
      "q": "Vad är cylinderns slagvolym?",
      "o": [
        "Trycket gånger arean",
        "Kolvarean gånger slaglängden",
        "Luftflödet per sekund",
        "Kraften dividerat med trycket"
      ],
      "a": 1,
      "e": "Slagvolym V = A × s, dvs. kolvarean multiplicerad med slaglängden."
    },
    {
      "c": "Cylindrar",
      "q": "I vilken enhet mäts cylinderns luftförbrukning?",
      "o": [
        "Bar",
        "Newton",
        "Normalliter (Nl)",
        "Kubikcentimeter per slag"
      ],
      "a": 2,
      "e": "Luftförbrukning mäts i normalliter (Nl) – volym vid normalbetingelser: 1 bar, +20°C, 65% relativ fuktighet."
    },
    {
      "c": "Cylindrar",
      "q": "Vad innebär ett dubbelslag för en cylinder?",
      "o": [
        "Att cylindern slår två gånger fort",
        "Kolvens ut- och inrörelse tillsammans",
        "Dubbel cylinderkraft",
        "Två cylindrar i serie"
      ],
      "a": 1,
      "e": "Luftförbrukning mäts per dubbelslag = kolvens utrörelse (tryckriktning) + inrörelse (dragriktning)."
    },
    {
      "c": "Cylindrar",
      "q": "Vad är en vridcylinder?",
      "o": [
        "En cylinder med cirkulärt lopp",
        "En cylinder som omvandlar linjär rörelse till roterande rörelse",
        "En cylinder monterad på en svängarm",
        "En cylinder med vridbart fäste"
      ],
      "a": 1,
      "e": "En vridcylinder omvandlar linjär kolvrörelse till roterande rörelse via en kuggstång eller vingmekanism."
    },
    {
      "c": "Cylindrar",
      "q": "Vad är ändlägesdämpning på en cylinder?",
      "o": [
        "En broms för hela cylindern",
        "En inbyggd dämpning som saktar ner kolven innan den når ändläget",
        "En fjäder i cylindern",
        "En sensor som stoppar cylindern"
      ],
      "a": 1,
      "e": "Ändlägesdämpning är en inbyggd luftkudde som saktar ner kolven de sista millimetrarna innan ändläget och skyddar mot slagkrafter."
    },
    {
      "c": "Cylindrar",
      "q": "Vilken cylindertyp lämpar sig bäst när kolvstången inte får vrida sig?",
      "o": [
        "Skyttelcylinder",
        "Cylinder med styrstänger",
        "Vridcylinder",
        "Kompaktcylinder utan dämpning"
      ],
      "a": 1,
      "e": "Cylinder med styrstänger – kolvstången kombineras med en styrd fästplatta med två styrstänger som hindrar vridning."
    },
    {
      "c": "Cylindrar",
      "q": "Vad är Normalluft enligt ISO-standard?",
      "o": [
        "Luft vid 6 bar och 20°C",
        "Luft vid 1 bar, +20°C och 65% relativ fuktighet",
        "Luft vid 0°C och 1 bar",
        "Torr luft vid 10 bar"
      ],
      "a": 1,
      "e": "ISO normerar Normalluft till: tryck 1 bar, temperatur +20°C, relativ fuktighet 65%."
    },
    {
      "c": "Cylindrar",
      "q": "Hur beräknas luftförbrukning Q per dubbelslag (normalliter)?",
      "o": [
        "Q = (V_T − V_D) × p",
        "Q = (V_T + V_D) × (p + p_atm) / p_atm",
        "Q = A × s × p",
        "Q = F / A"
      ],
      "a": 1,
      "e": "Q = (V_T + V_D) × (p + p_atm) / p_atm, där p_atm = 1 bar. Summerar volymerna i båda riktningarna och kompenserar för övertrycket."
    },
    {
      "c": "Cylindrar",
      "q": "En cylinder med Ø50 mm kolv har kolvstång Ø18 mm. Vilken area är störst?",
      "o": [
        "A₂ (dragsidan)",
        "A₁ (trycksidan)",
        "De är lika stora",
        "Det beror på trycket"
      ],
      "a": 1,
      "e": "A₁ = π×d²/4 = 19,6 cm². A₂ = A₁ − stångarea = 19,6 − 2,5 = 17,1 cm². Trycksidan A₁ är alltid störst."
    },
    {
      "c": "Cylindrar",
      "q": "Vad är en kompaktcylinder?",
      "o": [
        "En cylinder med lång slaglängd",
        "En cylinder med kort slaglängd och litet format",
        "En cylinder utan kolv",
        "En cylinder med extern dämpare"
      ],
      "a": 1,
      "e": "Kompaktcylinder har kort slaglängd och litet format – används för att spänna fast, pressa och låsa fast arbetsstycken."
    },
    {
      "c": "Cylindrar",
      "q": "Vad är en kostaloecylinder?",
      "o": [
        "En cylinder för höga temperaturer",
        "En cylinder med inbyggd låsmekanism",
        "En cylinder med kuggstångsdrift för rotering",
        "En cylinder med fjäderåtergång"
      ],
      "a": 2,
      "e": "Kostaloecylindern är ett vriddon där en kuggstång driver ett kugghjul och omvandlar linjär rörelse till rotation."
    },
    {
      "c": "Ventiler",
      "q": "Vilka tre storheter reglerar en riktningsventil i en pneumatisk anläggning?",
      "o": [
        "Kraft, hastighet och tid",
        "Riktning, tryck och flöde",
        "Frekvens, amplitud och fas",
        "Temperatur, tryck och volym"
      ],
      "a": 1,
      "e": "Ventiler reglerar riktning, tryck och flöde i den pneumatiska anläggningen."
    },
    {
      "c": "Ventiler",
      "q": "Vad är skillnaden mellan en effektventil och en signalgivande ventil?",
      "o": [
        "Effektventilen är elektrisk, signalventilen pneumatisk",
        "Effektventilen hanterar stora flöden, signalventilen hanterar bara tryckpulser",
        "De är identiska men monteras olika",
        "Effektventilen är backventil, signalventilen är riktningsventil"
      ],
      "a": 1,
      "e": "Effektventiler manövrerar ställdon med stora flöden. Signalgivande ventiler och logikelement hanterar bara tryckpulser för styrning."
    },
    {
      "c": "Ventiler",
      "q": "Vad innebär ventilbeteckningen 5/2?",
      "o": [
        "5 bar maxitryck, 2 sekunder svarstid",
        "5 anslutningar och 2 lägen",
        "5 mm flödeshål och 2 kg vikt",
        "5 Nl/s flöde och 2 bar drifttryck"
      ],
      "a": 1,
      "e": "5/2-ventil: 5 anslutningsportar (1 tryck, 2 arbetstryck, 2 avgaser) och 2 stycken stabila lägen."
    },
    {
      "c": "Ventiler",
      "q": "Vad innebär ventilbeteckningen 3/2?",
      "o": [
        "3 anslutningar och 2 lägen",
        "3 bar och 2 anslutningar",
        "3 sekunder och 2 slag",
        "3 lägen och 2 anslutningar"
      ],
      "a": 0,
      "e": "3/2-ventil: 3 anslutningsportar och 2 lägen. Vanlig för enkelverkande cylindrar och signalgivning."
    },
    {
      "c": "Ventiler",
      "q": "Hur konstrueras riktningsventiler?",
      "o": [
        "Som membranventiler eller nålventiler",
        "Som sätes- eller slidventiler",
        "Som backventiler eller tryckventiler",
        "Som manuella eller elektriska ventiler"
      ],
      "a": 1,
      "e": "Riktningsventiler konstrueras som sätes- eller slidventiler. Sätes = tätar med en kona/boll. Slid = en skjutbar cylinder stänger/öppnar kanaler."
    },
    {
      "c": "Ventiler",
      "q": "Vad avgör valet av ventilstorlek?",
      "o": [
        "Cylinderns slaglängd",
        "Det nominella flödet som ska passera",
        "Arbetstrycket",
        "Cylinderdiametern direkt"
      ],
      "a": 1,
      "e": "Ventilstorleken väljs efter det nominella flödet (Nl/s) som ska passera. Det nominella flödet är störst för effektventilerna."
    },
    {
      "c": "Ventiler",
      "q": "Vid vilket ingångstryck och tryckskillnad mäts normalt nominellt flöde?",
      "o": [
        "1 bar ingångstryck, 0,5 bar tryckfall",
        "6 bar ingångstryck och varierande tryckskillnad",
        "10 bar, 1 bar tryckfall",
        "3 bar, 3 bar tryckfall"
      ],
      "a": 1,
      "e": "Nominellt flöde mäts vid 6 bar ingångstryck med varierande tryckskillnad över ventilen. Kurvan visar flödets variation."
    },
    {
      "c": "Ventiler",
      "q": "Vad är en backventil?",
      "o": [
        "En ventil som öppnar vid högt tryck",
        "En ventil som bara släpper igenom flöde i en riktning",
        "En ventil med fjäderåtergång",
        "En ventil för extremt höga flöden"
      ],
      "a": 1,
      "e": "En backventil (check valve) tillåter flöde i bara en riktning och blockerar återflöde automatiskt."
    },
    {
      "c": "Ventiler",
      "q": "Vad är en strypbackventil?",
      "o": [
        "En backventil kombinerad med en strypventil – stryper i en riktning, fritt flöde i andra",
        "En ventil för vakuum",
        "En tryckregulerande ventil",
        "En ventil med tidsfördröjning"
      ],
      "a": 0,
      "e": "Strypbackventil kombinerar en backventil med strypventil: stryper flödet i en riktning men tillåter fritt flöde i den andra. Används för hastighetsstyrning."
    },
    {
      "c": "Ventiler",
      "q": "Vad är tryckfall i ett pneumatiskt system?",
      "o": [
        "Trycket i cylindern vid ändläge",
        "Skillnaden i tryck före och efter en komponent",
        "Det maximala arbetstrycket",
        "Trycket i kompressorn"
      ],
      "a": 1,
      "e": "Tryckfall uppstår när luft passerar en ledning eller komponent. Ju klenare dimension desto större tryckfall. För stora tryckfall kan tvinga fram större cylindrar."
    },
    {
      "c": "Ventiler",
      "q": "Vad är C-värdet för en ventil?",
      "o": [
        "Kapacitetsvärdet som beskriver ventilens flödesförmåga",
        "Cylinderdiametern i cm",
        "Trycket i bar vid nominellt flöde",
        "Ventilens svarstid i millisekunder"
      ],
      "a": 0,
      "e": "C-värdet (kapacitetsvärde) är ett internationellt mått på en ventils eller komponents förmåga att släppa igenom luftflöde. Högt C = stort flöde."
    },
    {
      "c": "Ventiler",
      "q": "Hur monteras en anslutningsplatta (manifold) för ventiler?",
      "o": [
        "Direkt på cylindern",
        "Flera ventiler monteras på ett gemensamt block med gemensamma tryckingångar och avgaser",
        "På sidan av kompressorn",
        "Separata för varje krets"
      ],
      "a": 1,
      "e": "Anslutningsplattor möjliggör att flera ventiler monteras på ett block med gemensamma tryckinmatning och avgaskanaler – sparar plats och förenklar installation."
    },
    {
      "c": "Ventiler",
      "q": "Vad är tryckregulatorn till för?",
      "o": [
        "Att öka trycket över kompressortrycket",
        "Att hålla ett konstant, inställt drifttryck oavsett flödesvariation",
        "Att filtrera luften",
        "Att mäta trycket"
      ],
      "a": 1,
      "e": "Tryckregulatorn håller ett konstant inställt drifttryck i systemet oberoende av flödesvariationer och kompressortrycksvariationer."
    },
    {
      "c": "Ventiler",
      "q": "Vilka ventilgrupper används i pneumatiken?",
      "o": [
        "Tryckventiler och flödesventiler",
        "Riktningsventiler, backventiler, tryckstyrande ventiler och flödesstyrande ventiler",
        "Magnetventiler och manövreringsventiler",
        "Säkerhetsventiler och normalventiler"
      ],
      "a": 1,
      "e": "De fyra ventilgrupperna: riktningsventiler (styr riktning), backventiler (en riktning), tryckstyrande (tryckfall/regulator), flödesstyrande (strypventiler)."
    },
    {
      "c": "Gripdon",
      "q": "Vilka tre principtyper av gripdon finns?",
      "o": [
        "Pneumatiska, hydrauliska och elektriska",
        "Mekaniska, magnetiska och vakuumdrivna",
        "Fingrar, sugkoppar och magneter",
        "Parallell-, vinkel- och centralgripdon"
      ],
      "a": 1,
      "e": "Gripdon kan vara mekaniska (parallella fingrar), magnetiska eller vakuumdrivna (sugkoppar). Valet beror på föremålets material och form."
    },
    {
      "c": "Gripdon",
      "q": "Vilken drivning är vanligast för mekaniska gripdon?",
      "o": [
        "Elektrisk motor",
        "Hydraulik",
        "Pneumatisk cylinder med ventil",
        "Manuell fjäderbelastning"
      ],
      "a": 2,
      "e": "Mekaniska gripdon drivs oftast pneumatiskt med en enkel- eller dubbelkolv i gripdonen, styrd av en ventil."
    },
    {
      "c": "Gripdon",
      "q": "Hur bildas vakuum i ett vakuumgripdon?",
      "o": [
        "Med en elektrisk vakuumpump alltid",
        "Med en pneumatisk ejektor som accelererar luft och skapar undertryck",
        "Genom att stänga en ventil och vänta",
        "Med en membranpump"
      ],
      "a": 1,
      "e": "Ejektorn ansluts till tryckluften. Luften accelereras genom en strypning, luften från sugkoppen medföljer och skapar undertryck (vakuum)."
    },
    {
      "c": "Gripdon",
      "q": "Vilka är fördelarna med vakuumgripdon?",
      "o": [
        "Griper bara metall",
        "Billigt, hanterar de flesta material, klarar ömtåliga föremål och räcker med ungefärlig positionering",
        "Kräver exakt positionering",
        "Kräver högt övertryck"
      ],
      "a": 1,
      "e": "Vakuumgripdon är billiga, hanterar de flesta material (papper, plåt, glas), klarar ömtåliga material och kräver inte exakt positionering."
    },
    {
      "c": "Gripdon",
      "q": "Vilken typ av sugkopp används för icke-plana eller ojämna ytor?",
      "o": [
        "Plan sugkopp",
        "Liten sugkopp",
        "Bälgsugkopp",
        "Oval sugkopp"
      ],
      "a": 2,
      "e": "Bälgsugkoppen har en balg (veckat gummi) som kan anpassa sig till ojämna eller lätt böjda ytor."
    },
    {
      "c": "Gripdon",
      "q": "Vad beror valet av sugkoppsmaterial på?",
      "o": [
        "Enbart priset",
        "Oljebeständighet, slitstyrka, väderbeständighet, temperaturområde och miljöaspekter",
        "Bara föremålets vikt",
        "Vakuumgeneratorns kapacitet"
      ],
      "a": 1,
      "e": "Sugkoppsmaterial väljs efter: oljebeständighet, slitstyrka, väderbeständighet, temperaturområde och miljöaspekter."
    },
    {
      "c": "Gripdon",
      "q": "Vad är skillnaden mellan dimensionering för horisontellt och vertikalt lyft med sugkopp?",
      "o": [
        "Ingen skillnad",
        "Vid horisontellt lyft krävs större sugkopp pga. skjuv-/friktionskrafter",
        "Vertikalt lyft kräver alltid dubbelt så stor sugkopp",
        "Horisontellt lyft kräver vakuumpump, vertikalt räcker ejektor"
      ],
      "a": 1,
      "e": "Vid horisontellt lyft (skjuvkraft) måste sugkoppens greppkraft vara högre än vid vertikalt lyft (direkt dragkraft), eftersom friktionskoefficienten mot föremålet påverkar."
    },
    {
      "c": "Gripdon",
      "q": "Varför används tryckregulatorer i mekaniska gripdon?",
      "o": [
        "För att öka griphastigheten",
        "För att ställa in gripkraften på rätt nivå",
        "För att filtrera luften",
        "För att styra grippositionen"
      ],
      "a": 1,
      "e": "Tryckregulatorn ställer in lufttrycket och därmed gripkraften. Rätt gripkraft skyddar ömtåliga detaljer och ger korrekt hållkraft."
    },
    {
      "c": "Gripdon",
      "q": "Vad är en ejektor?",
      "o": [
        "En elektrisk pump för vakuum",
        "En pneumatisk komponent som skapar vakuum via Venturiprincipen",
        "En typ av backventil",
        "En tryckmätare"
      ],
      "a": 1,
      "e": "En ejektor utnyttjar Venturieffekten: tryckluften accelereras i en strypning och drar med sig luft från sugkoppen, vilket skapar undertryck (vakuum)."
    },
    {
      "c": "Sensorer",
      "q": "Vad är en sensor uppbyggd av?",
      "o": [
        "En avkännare och en lysdiod",
        "Avkännande element + signalbehandlare/förstärkare",
        "Tryckgivare och temperatursensor",
        "Magnetkärna och kolvstång"
      ],
      "a": 1,
      "e": "Sensor = avkännande element (reagerar på instorheten) + signalbehandlare/förstärkare (omvandlar och förstärker signalen till användbar utsignal)."
    },
    {
      "c": "Sensorer",
      "q": "Vad är skillnaden mellan en analog och en binär sensorsignal?",
      "o": [
        "Analog är digital, binär är analogt",
        "Analog är proportionell mot instorheten, binär ger bara TILL/FRÅN",
        "Binär ger mer noggrann mätning",
        "Analog används bara för temperatur"
      ],
      "a": 1,
      "e": "Analog signal är proportionell mot instorheten (kontinuerlig). Binär signal är antingen TILL eller FRÅN – rapporterar ett ändläge eller närvaro/frånvaro."
    },
    {
      "c": "Sensorer",
      "q": "Vad avkänner en magnetkolvsavkännare?",
      "o": [
        "Temperatur i cylindern",
        "Cylinderns lufttryck",
        "Kolvens läge via permanentmagnet i kolven",
        "Kolvstångens böjning"
      ],
      "a": 2,
      "e": "Magnetkolvsavkännaren monteras på cylindern och reagerar på den permanentmagnet som sitter i kolven – ger signal när kolven passerar sensorn."
    },
    {
      "c": "Sensorer",
      "q": "Hur fungerar en induktiv sensor?",
      "o": [
        "Utsänder infraröd ljus och mäter reflexen",
        "Alstrar ett magnetfält och registrerar störningar från metallföremål via virvelströmmar",
        "Mäter kapacitansen till alla föremål",
        "Registrerar magnetfält från permanentmagneter"
      ],
      "a": 1,
      "e": "Induktiv sensor alstrar ett magnetfält. Metallföremål i fältet skapar virvelströmmar som ändrar sensorns induktans – sensorn aktiveras."
    },
    {
      "c": "Sensorer",
      "q": "Vilka material detekterar en induktiv sensor bäst?",
      "o": [
        "Plast och gummi",
        "Ferromagnetiska metaller (järn, stål)",
        "Alla material utan undantag",
        "Bara koppar och aluminium"
      ],
      "a": 1,
      "e": "Induktiva sensorer fungerar bäst på ferromagnetiska material. För icke-magnetiska metaller (aluminium, koppar) måste avkänningsavståndet reduceras med reduktionsfaktor."
    },
    {
      "c": "Sensorer",
      "q": "Vilken reduktionsfaktor gäller för aluminium vid induktiv avkänning?",
      "o": [
        "0,9 × Kn",
        "0,7 × Kn",
        "0,4 × Kn",
        "1,0 × Kn"
      ],
      "a": 2,
      "e": "För aluminium (och koppar) gäller reduktionsfaktor 0,4 × Kn (nominellt avkänningsavstånd). Kn reduceras kraftigt för icke-magnetiska metaller."
    },
    {
      "c": "Sensorer",
      "q": "Hur fungerar en kapacitiv sensor?",
      "o": [
        "Via magnetfält och virvelströmmar",
        "Via ett elektriskt fält som störs av föremål i närheten oavsett material",
        "Via ljusstråle och reflektion",
        "Via tryckskillnad"
      ],
      "a": 1,
      "e": "Kapacitiv sensor utnyttjar ett elektriskt fält. Föremålet stör fältet och ändrar kapacitansen – fungerar på metall, plast, trä, glas och vätskor."
    },
    {
      "c": "Sensorer",
      "q": "Vad är fördelen med kapacitiva sensorer jämfört med induktiva?",
      "o": [
        "Längre avkänningsavstånd",
        "Kan detektera alla material – även plast, glas och vätskor",
        "Tåligare i smutsiga miljöer",
        "Ger analog signal alltid"
      ],
      "a": 1,
      "e": "Kapacitiva sensorer kan avkänna praktiskt taget alla material – metall, plast, trä, glas, vätskor och granulat, till skillnad från induktiva som kräver metall."
    },
    {
      "c": "Sensorer",
      "q": "Vilka är de fyra metoderna för optisk avkänning?",
      "o": [
        "Analog, binär, digital och trådlös",
        "Envägsavkänning, reflexavkänning, direktavkänning och direktavkänning med bakgrundsdämpning",
        "Infraröd, laser, UV och synlig",
        "Reflektion, transmission, diffusion och fluorescens"
      ],
      "a": 1,
      "e": "Optiska sensorer används i fyra lägen: envägs (sändare+mottagare), reflex (reflektor), direkt (mot föremålet), direkt med bakgrundsdämpning (ställbar räckvidd)."
    },
    {
      "c": "Sensorer",
      "q": "Vad är fördelen med envägsavkänning (optisk)?",
      "o": [
        "Enklast att montera",
        "Högst immunitet mot störljus och bakgrundsreflexer – säkrast avkänning",
        "Billigast lösning",
        "Ger analog signal"
      ],
      "a": 1,
      "e": "Envägsavkänning ger högst känslighet och störimmunitet – sändaren och mottagaren sitter på var sin sida av detektionspunkten."
    },
    {
      "c": "Sensorer",
      "q": "Varför ska sensorledningar inte dras tillsammans med spänningstarka ledningar?",
      "o": [
        "Det är onödigt dyrt",
        "Höga spänningsstoppar och störningsfält stör sensorsignalen – skärmad kabel rekommenderas",
        "Det bryter mot säkerhetsregler alltid",
        "Ledningarna blandas ihop"
      ],
      "a": 1,
      "e": "Ledningar med höga spänningstoppar eller störningsfält kan störa svaga sensorsignaler. Skärmad anslutningsledning rekommenderas alltid."
    },
    {
      "c": "Sensorer",
      "q": "Vad är en transmitter i industriell kontext?",
      "o": [
        "En radiosändare",
        "En enhet som lämnar standardiserad utsignal, t.ex. 4–20 mA eller 0–5 V",
        "En typ av optisk sensor",
        "En magnetkolvsavkännare"
      ],
      "a": 1,
      "e": "En transmitter är en sensor/givare som lämnar en standardiserad utsignal (ex. 4–20 mA) – vanlig inom processindustri för tryckmätning, flödesmätning etc."
    },
    {
      "c": "Styrsystem",
      "q": "Vilka fem huvuddelar ingår i ett PLC-system?",
      "o": [
        "Motor, växel, axel, koppling och bromsar",
        "CPU (processor), minne, ingångsinterface, utgångsinterface och kraftenhet",
        "Sensor, ventil, cylinder, gripdon och transportör",
        "Kompressor, filter, regulator, ventil och cylinder"
      ],
      "a": 1,
      "e": "PLC-systemet består av: processor (CPU), minne, ingångsinterface (kopplar sensorer), utgångsinterface (kopplar ställdon) och kraftenhet (strömförsörjning)."
    },
    {
      "c": "Styrsystem",
      "q": "Vad är skillnaden mellan analog och digital (binär) utsignal från en PLC?",
      "o": [
        "Analog ger TILL/FRÅN, digital ger kontinuerlig signal",
        "Digital ger TILL/FRÅN, analog ger proportionell utsignal",
        "De är identiska",
        "Analog är bara för ingångar"
      ],
      "a": 1,
      "e": "Digital (binär) utsignal = TILL eller FRÅN (t.ex. aktivera en magnetventil). Analog utsignal = proportionell signal (ex. 4–20 mA för hastighetsstyrning)."
    },
    {
      "c": "Styrsystem",
      "q": "Vad är ett fältbussystem?",
      "o": [
        "Ett separat kablage för varje enhet",
        "Ett system där signaler sänds seriellt på ett gemensamt kabelpar mellan PLC och alla enheter",
        "En typ av pneumatisk ledning",
        "En speciell typ av magnetventil"
      ],
      "a": 1,
      "e": "Fältbuss: PLC kommunicerar med sensorer, ventiler och I/O-enheter via ett gemensamt kabelpar (seriell kommunikation) istället för parallell kabeldragning per signal."
    },
    {
      "c": "Styrsystem",
      "q": "Vilken fördel ger fältbuss jämfört med parallell kabeldragning?",
      "o": [
        "Snabbare enskilda signaler",
        "Kraftigt reducerad kabelmängd, enklare installation och felsökning",
        "Högre maximal frekvens",
        "Billigare PLC-hårdvara"
      ],
      "a": 1,
      "e": "Fältbuss reducerar kabelantalet drastiskt: alla signaler sänds seriellt på ett kabelpar. Förenklar installation, underhåll och kommunikation med externa system."
    },
    {
      "c": "Styrsystem",
      "q": "Vad menas med PLC:ns svarstid?",
      "o": [
        "Hur lång tid det tar att programmera PLC:n",
        "Tid från att en insignal aktiveras till att rätt utsignal ges",
        "Hur lång tid PLC:n kan köra utan service",
        "Cykeltiden för ett program"
      ],
      "a": 1,
      "e": "Svarstid = tid från att en insignal ändras tills PLC:n har bearbetat det och gett rätt utsignal. Viktigt för tidskritiska applikationer."
    },
    {
      "c": "Styrsystem",
      "q": "Vad avgör hur många I/O-punkter en PLC behöver?",
      "o": [
        "Processorns hastighet",
        "Antalet sensorer (ingångar) och ställdon (utgångar) i anläggningen",
        "Minnets storlek",
        "Fabrikatets standardkonfiguration"
      ],
      "a": 1,
      "e": "Antal I/O-punkter bestäms av anläggningens sensorer (digitala/analoga ingångar) och ställdon (ventiler, motorer – utgångar). Ofta tillägg för framtida expansion."
    },
    {
      "c": "Styrsystem",
      "q": "Vad innebär intern kraftkälla i en PLC?",
      "o": [
        "PLC:n har ett batteri",
        "PLC:n matar ut ström till sensorer och ställdon från sin egna strömförsörjning",
        "PLC:n är nätoberoende",
        "PLC:n styr kompressorn"
      ],
      "a": 1,
      "e": "PLC med intern kraftkälla kan mata sensorer och vissa ställdon direkt. Extern kraftkälla innebär att separat strömförsörjning krävs för utgångarna."
    },
    {
      "c": "Styrsystem",
      "q": "Vad är en I/O-enhet (decentraliserad) i fältbussystem?",
      "o": [
        "En extra PLC",
        "En lokal enhet nära ställdon/sensorer som kopplas till fältbussen och kommunicerar med PLC:n",
        "En operatörspanel",
        "En nätverksswitch"
      ],
      "a": 1,
      "e": "Decentraliserad I/O-enhet placeras nära ställdonen/sensorerna. Alla lokala signaler samlas i enheten och sänds seriellt via fältbuss till PLC:n – minskar kabeldragning."
    },
    {
      "c": "Beräkningar",
      "q": "En cylinder har Ø20 mm kolv. Beräkna A₁ (kolvarea) i cm².",
      "o": [
        "1,57 cm²",
        "3,14 cm²",
        "6,28 cm²",
        "12,57 cm²"
      ],
      "a": 1,
      "e": "A = π × d²/4 = π × 2²/4 = 3,14 cm². (Ø20 mm = 2 cm, d²=4, /4=1, ×π=3,14)"
    },
    {
      "c": "Beräkningar",
      "q": "En cylinder med A₁ = 3,14 cm² körs vid 6 bar. Vad är den teoretiska tryckkraften?",
      "o": [
        "18,8 N",
        "188 N",
        "1 884 N",
        "31,4 N"
      ],
      "a": 1,
      "e": "F_teor = p × A = 6 bar × 3,14 cm² = 6 × 31,4 N/bar = 188,4 N ≈ 188 N. (1 bar × 1 cm² = 10 N)"
    },
    {
      "c": "Beräkningar",
      "q": "Hur stor är den verkliga cylinderkraften om F_teor = 500 N?",
      "o": [
        "500 N",
        "450 N",
        "350 N",
        "325 N"
      ],
      "a": 2,
      "e": "F_verk = F_teor × (1 − 0,3) = 500 × 0,7 = 350 N. (Friktions- och accelerationsförluster = 30% totalt)"
    },
    {
      "c": "Beräkningar",
      "q": "En cylinder Ø50 mm, kolvstång Ø18 mm, slaglängd 250 mm. Beräkna slagvolym V_T (tryckriktning) i cm³.",
      "o": [
        "245 cm³",
        "490 cm³",
        "19,6 cm³",
        "196 cm³"
      ],
      "a": 1,
      "e": "A₁ = π × 5²/4 = 19,6 cm². V_T = A₁ × s = 19,6 × 25 = 490 cm³. (250 mm = 25 cm)"
    },
    {
      "c": "Beräkningar",
      "q": "Samma cylinder Ø50/18 mm, slag 250 mm. Beräkna V_D (dragriktning) i cm³.",
      "o": [
        "490 cm³",
        "413 cm³",
        "245 cm³",
        "500 cm³"
      ],
      "a": 1,
      "e": "A_stång = π × 1,8²/4 = 2,54 cm². A₂ = 19,6 − 2,54 = 17,1 cm² (≈16,5 i tabellen). V_D = 16,5 × 25 = 413 cm³."
    },
    {
      "c": "Beräkningar",
      "q": "Beräkna luftförbrukning Q per dubbelslag för cylindern (V_T=490, V_D=413 cm³) vid 6 bar.",
      "o": [
        "903 cm³",
        "6321 cm³",
        "1806 Nl",
        "490 Nl"
      ],
      "a": 1,
      "e": "Q = (490+413) × (6+1)/1 = 903 × 7 = 6321 cm³ = 6,321 dm³ = 6,321 Nl per dubbelslag."
    },
    {
      "c": "Beräkningar",
      "q": "Om cylindern gör 5 dubbelslag per minut, hur mycket luft förbrukas per minut?",
      "o": [
        "6,3 Nl/min",
        "31,6 Nl/min",
        "63 Nl/min",
        "316 Nl/min"
      ],
      "a": 1,
      "e": "Q_min = 6,321 Nl × 5 slag/min = 31,6 Nl/min."
    },
    {
      "c": "Beräkningar",
      "q": "Vilket tryck behövs för att en cylinder med A₁ = 19,6 cm² ska ge en aktionskraft på 1000 N (teoretisk)?",
      "o": [
        "1 bar",
        "3,1 bar",
        "5,1 bar",
        "10,2 bar"
      ],
      "a": 2,
      "e": "p = F/A = 1000 N / 19,6 cm² = 51 N/cm² = 5,1 bar. (10 N/cm² = 1 bar)"
    },
    {
      "c": "Beräkningar",
      "q": "En skyttelcylinder Ø16 mm körs vid 6 bar. Kolvarean A = 2,01 cm². Vad är F_teor?",
      "o": [
        "12 N",
        "120,6 N",
        "201 N",
        "60 N"
      ],
      "a": 1,
      "e": "F_teor = p × A = 6 × 2,01 × 10 = 120,6 N. (6 bar × 2,01 cm² × 10 N per bar·cm²)"
    },
    {
      "c": "Beräkningar",
      "q": "Friktionskraften på en cylinder är 5% av F_teor = 200 N. Hur stor är friktionskraften?",
      "o": [
        "5 N",
        "10 N",
        "15 N",
        "20 N"
      ],
      "a": 1,
      "e": "F_frikt = 0,05 × 200 = 10 N. Friktionskrafterna uppskattas till 5% av den teoretiska kraften."
    }
  ],
  "flashcards": [
    {
      "c": "Cylindrar",
      "t": "Aktionskraft",
      "d": "Den kraft kolvstången i en cylinder utvecklar. Beräknas som F = p × A (tryck × kolvarean). Är olika i tryck- och dragriktningen för dubbelverkande cylindrar."
    },
    {
      "c": "Cylindrar",
      "t": "F_teor vs F_verk",
      "d": "Teoretisk kraft: F = p × A. Verklig kraft: F = p × A × (1−0,3) – 30% förlust pga. friktionskrafter (5%) och accelerationskrafter (25%)."
    },
    {
      "c": "Cylindrar",
      "t": "Dubbelverkande cylinder",
      "d": "Cylinder med kolvstång som kan drivas i båda riktningarna med tryckluft. Tryckkraft (A₁) > Dragkraft (A₂) eftersom kolvstångsarean räknas bort på dragsidan."
    },
    {
      "c": "Cylindrar",
      "t": "Skyttelcylinder",
      "d": "Cylinder utan traditionell kolvstång, med genomgående stång för skyttelrörelse. Aktionskraften lika i båda riktningarna. Kolvdiameter 16 mm i AUTOBYGG."
    },
    {
      "c": "Cylindrar",
      "t": "Linjärmodul",
      "d": "Två sammanbyggda cylindrar (dubbla kolvar) i ett kompakt hus. Klarar stora tvärkrafter. Kan ha hålad kolvstång för vakuumapplikation och inbyggd ändlägesgivare."
    },
    {
      "c": "Cylindrar",
      "t": "Slagvolym V",
      "d": "V = A × s (kolvarean × slaglängd). V_T (tryckriktning) = A₁ × s. V_D (dragriktning) = A₂ × s. Anges i cm³ eller dm³."
    },
    {
      "c": "Cylindrar",
      "t": "Luftförbrukning Q per dubbelslag",
      "d": "Q = (V_T + V_D) × (p + p_atm) / p_atm. Resultatet i cm³ → dela med 1000 för Nl. Normalbetingelser: 1 bar, +20°C, 65% RF."
    },
    {
      "c": "Cylindrar",
      "t": "Ändlägesdämpning",
      "d": "Inbyggd luftkudde som saktar ner kolven de sista mm före ändläget. Skyddar mekanik från slagkrafter. Kan vara fast eller justerbar."
    },
    {
      "c": "Cylindrar",
      "t": "Cylinderfästen",
      "d": "Gavelfäste (ändmontage), fotfäste (sidomontage), avkännarfäste. På cylindern monteras också magnetkolvsavkännare för lägesdetektering."
    },
    {
      "c": "Cylindrar",
      "t": "Vriddon",
      "d": "Omvandlar linjär kolvrörelse till roterande rörelse. Utföranden: kuggstångscylinder (kostalo), vingcylinder. Vridvinkel typiskt 90°, 180° eller 270°."
    },
    {
      "c": "Cylindrar",
      "t": "Normalluft (ISO)",
      "d": "Referenstillstånd för luftmätning: 1 bar absoluttryck, +20°C temperatur, 65% relativ fuktighet. Normalliter (Nl) = liter luft vid dessa betingelser."
    },
    {
      "c": "Cylindrar",
      "t": "Kolvarean A",
      "d": "A = π × d²/4. Enhet: cm². Exempeldata: Ø8mm→0,5cm², Ø20mm→3,14cm², Ø50mm→19,6cm², Ø80mm→50cm², Ø125mm→122cm²."
    },
    {
      "c": "Ventiler",
      "t": "Riktningsventil 5/2",
      "d": "5 anslutningsportar (1 tryck, 2 arbetstryck, 2 avgaser) och 2 stabila lägen. Standardventil för dubbelverkande cylindrar."
    },
    {
      "c": "Ventiler",
      "t": "Riktningsventil 3/2",
      "d": "3 anslutningsportar och 2 lägen. Normalt stängd (NC) eller normalt öppen (NO). Används för enkelverkande cylindrar och signalgivning."
    },
    {
      "c": "Ventiler",
      "t": "Effektventil vs signalventil",
      "d": "Effektventil: styr ställdon, hanterar stora flöden. Signalgivande ventil/logikelement: bearbetar bara tryckpulser för styrlogik, litet flöde."
    },
    {
      "c": "Ventiler",
      "t": "Sätes- och slidventil",
      "d": "Sätes (poppet): tätar med kona/boll mot säte. Slidventil: skjutbar cylinder öppnar/stänger kanaler. Sätes är läcksäkrare, slid ger fler portmöjligheter."
    },
    {
      "c": "Ventiler",
      "t": "Strypbackventil",
      "d": "Kombinerar backventil + strypventil. Stryper flödet i en riktning (justerbar), fritt flöde i andra riktningen. Används för att styra cylinderhastighet i en riktning."
    },
    {
      "c": "Ventiler",
      "t": "Backventil",
      "d": "Tillåter flöde i bara en riktning. Blockerar automatiskt återflöde utan yttre styrning. Vanlig i kretsar med tryckreservering och enkelriktad rörelse."
    },
    {
      "c": "Ventiler",
      "t": "Tryckfall i ledning",
      "d": "Tryckfall uppstår när luft passerar ledning eller komponent. Klenare dimension → större tryckfall. Formel för ledning: p_LD = Δp × l × (7/8pl + 1). Δp avläses ur diagram vid aktuellt flöde och ingångstryck."
    },
    {
      "c": "Ventiler",
      "t": "Tryckregulatorn",
      "d": "Håller konstant inställt drifttryck oavsett flödes- och kompressortryckvariationer. Primär komponent i luftbehandlingsenheten (FRL: filter-regulator-smörjare)."
    },
    {
      "c": "Ventiler",
      "t": "C-värde (kapacitetsvärde)",
      "d": "Internationellt mått på komponents flödesförmåga. Högt C = stort flöde. Används för att beräkna och jämföra ventilers och ledningars kapacitet."
    },
    {
      "c": "Ventiler",
      "t": "Anslutningsplatta (manifold)",
      "d": "Block för att montera flera ventiler med gemensam tryckinmatning och avgaskanaler. Sparar plats, minskar ledningsdragning och förenklar installation."
    },
    {
      "c": "Ventiler",
      "t": "Nominellt flöde",
      "d": "Uppmätt flöde (Nl/s) vid 6 bar ingångstryck med varierande tryckskillnad. Avgör ventilstorleken – störst krav ställs på effektventilerna."
    },
    {
      "c": "Gripdon",
      "t": "Mekaniskt gripdon",
      "d": "Parallella fingrar drivna pneumatiskt. Fingrar rör sig mot varandra och klämer föremålet. Kan ha fjäderbelastade fingrar som klämmer som tång."
    },
    {
      "c": "Gripdon",
      "t": "Vakuumgripdon – ejektor",
      "d": "Tryckluften accelereras i en strypning (Venturi) → drar med sig luft från sugkoppen → skapar undertryck. Alternativ: vakuumpump. Fördel: enkel, kompakt, inget elbruk."
    },
    {
      "c": "Gripdon",
      "t": "Sugkoppstyper",
      "d": "Plan (plana ytor), liten (smala detaljer), bälg (ojämna ytor), plan med utbytbar läpp, plan och oval. Val baseras på föremålets form och lyftmetod."
    },
    {
      "c": "Gripdon",
      "t": "Dimensionering sugkopp",
      "d": "Horisontellt lyft (skjuv): F_grip > G/μ. Vertikalt lyft: F_grip > G. Säkerhetsfaktor 2–4 används. G = föremålets tyngd (N). μ = friktionskoefficient."
    },
    {
      "c": "Gripdon",
      "t": "Fördelar vakuumgripdon",
      "d": "Billigt gripsystem · Hanterar de flesta material (papper, plåt, glas, plast) · Klarar ömtåliga material · Räcker med ungefärlig positionering · Enkel styrning"
    },
    {
      "c": "Gripdon",
      "t": "Vakuum – definition",
      "d": "'Ett lufttomt rum eller en del av rymden utan närvaro av material.' I teknik: undertryck under atmosfärtrycket (1 bar). Mäts i mbar undertryck."
    },
    {
      "c": "Sensorer",
      "t": "Sensor – uppbyggnad",
      "d": "Sensor = avkännande element (påverkas direkt av instorheten) + signalbehandlare/förstärkare (omvandlar svag signal till användbar utsignal + LED-indikering)."
    },
    {
      "c": "Sensorer",
      "t": "Magnetkolvsavkännare",
      "d": "Monteras utanpå cylinderröret. Detekterar permanentmagneten i kolven. Ger binär signal (TILL/FRÅN) när kolven passerar. Steglös inställning längs cylindern."
    },
    {
      "c": "Sensorer",
      "t": "Induktiv sensor",
      "d": "Alstrar magnetfält → metallobjekt skapar virvelströmmar → ändrar induktansen → sensorn aktiveras. Fungerar bäst på ferromagnetiska metaller. Kontaktfri."
    },
    {
      "c": "Sensorer",
      "t": "Reduktionsfaktor – induktiv sensor",
      "d": "Icke-ferromagnetiska metaller kräver reducerat avkänningsavstånd: Kromnickel 0,9×Kn · Mässing 0,5×Kn · Aluminium 0,4×Kn · Koppar 0,4×Kn"
    },
    {
      "c": "Sensorer",
      "t": "Kapacitiv sensor",
      "d": "Utnyttjar elektriskt fält. Föremål stör fältet och ändrar kapacitansen. Avkänner alla material: metall, plast, glas, trä, vätskor, granulat. Ej begränsad till metall."
    },
    {
      "c": "Sensorer",
      "t": "Optisk sensor – envägsavkänning",
      "d": "Sändare på en sida, mottagare på andra. Föremål bryter ljusstrålen → aktivering. Högst immunitet mot bakgrundsljus. Kräver åtkomst på båda sidor."
    },
    {
      "c": "Sensorer",
      "t": "Optisk sensor – reflexavkänning",
      "d": "Sändare och mottagare i samma enhet. Reflektor på andra sidan återspeglar ljuset. Föremål bryter strålen. Enklare montering än envägs men lägre räckvidd."
    },
    {
      "c": "Sensorer",
      "t": "Optisk sensor – direktavkänning",
      "d": "Sändare och mottagare i samma enhet. Avkänner reflexen från föremålet direkt. Kortare räckvidd. Med bakgrundsdämpning: inställbar räckvidd, ignorerar bakgrund."
    },
    {
      "c": "Sensorer",
      "t": "Avkännare, transmitter, detektor, vakt",
      "d": "Avkännare: pneumatik/ändlägen. Transmitter: standardsignal (4–20mA, 0–5V). Detektor: larm (ljus/ljud/rök/rörelse). Vakt: driftövervakning av temperaturer/tryck/flöden."
    },
    {
      "c": "Sensorer",
      "t": "Analog vs binär sensorsignal",
      "d": "Analog: proportionell mot instorheten, kontinuerlig (ex. 4–20mA för tryck 0–10 bar). Binär: TILL eller FRÅN – rapporterar ändläge eller närvaro/frånvaro."
    },
    {
      "c": "Styrsystem",
      "t": "PLC – uppbyggnad",
      "d": "Programmerbar logikstyrning. Delar: CPU (processor) · Minne · Ingångsinterface (kopplar sensorer) · Utgångsinterface (kopplar ställdon) · Kraftenhet"
    },
    {
      "c": "Styrsystem",
      "t": "PLC – signaltyper",
      "d": "Digitala ingångar: sensorer/brytare (0/1). Analoga ingångar: 4–20mA, 0–10V. Digitala utgångar: magnetventiler, lampor. Analoga utgångar: frekvensomriktare, proportionalventiler."
    },
    {
      "c": "Styrsystem",
      "t": "Fältbussystem",
      "d": "Seriell kommunikation på ett kabelpar (2 trådar) mellan PLC och decentraliserade I/O-enheter, sensorer och ventiler. Ersätter parallell kabeldragning och minskar kabelmassan kraftigt."
    },
    {
      "c": "Styrsystem",
      "t": "Fältbuss – fördelar",
      "d": "Drastiskt minskad kabelmängd · Enklare installation och driftsättning · Förenklad felsökning · Möjlighet till kommunikation med externa datorsystem · Decentraliserad I/O"
    },
    {
      "c": "Styrsystem",
      "t": "PLC – val av storlek",
      "d": "Baseras på: antal I/O-punkter (sensorer + ställdon) · Kommunikationsförmåga · Programkapacitet · Intern/extern kraftkälla · Svarstid · Kostnad"
    },
    {
      "c": "Styrsystem",
      "t": "Decentraliserad I/O-enhet",
      "d": "Placeras nära ställdon/sensorer. Samlar lokala signaler och kommunicerar med PLC via fältbuss. Minskar kabeldragning drastiskt i stora anläggningar."
    },
    {
      "c": "Styrsystem",
      "t": "Standard i europeisk industri – signal",
      "d": "Standardiserade signaler: 4–20 mA (analogt strömloop) · 0–10 V (analogt spänning) · 24 VDC (digitalt) · Möjliggör utbytbarhet mellan fabrikat."
    },
    {
      "c": "Beräkningar",
      "t": "Formel: Teoretisk cylinderkraft",
      "d": "F_teor = p × A [bar × cm²] = N/bar × bar = N. OBS: 1 bar × 1 cm² = 10 N. Eller: p i Pa × A i m² = N."
    },
    {
      "c": "Beräkningar",
      "t": "Formel: Verklig cylinderkraft",
      "d": "F_verk = p × A × (1 − 0,30) = F_teor × 0,70. De 30% = friktionskrafter (5%) + accelerationskrafter (25%)."
    },
    {
      "c": "Beräkningar",
      "t": "Formel: Kolvarean",
      "d": "A = π × d²/4. d i cm → A i cm². Exempel: d=2cm → A = 3,14×4/4 = 3,14 cm². d=5cm → A = 3,14×25/4 = 19,6 cm²."
    },
    {
      "c": "Beräkningar",
      "t": "Formel: Slagvolym",
      "d": "V_T = A₁ × s (tryckriktning). V_D = A₂ × s (dragriktning). A i cm², s i cm → V i cm³. 1 dm³ = 1000 cm³ = 1 Nl vid normalbetingelser."
    },
    {
      "c": "Beräkningar",
      "t": "Formel: Luftförbrukning per dubbelslag",
      "d": "Q = (V_T + V_D) × (p + p_atm) / p_atm. p_atm = 1 bar. Resultat i samma enhet som volymerna. cm³ → /1000 = Nl."
    },
    {
      "c": "Beräkningar",
      "t": "Formel: Erforderligt tryck",
      "d": "p = F / A. F i N, A i cm². Resultat i N/cm². Dela med 10 för att få bar. Exempel: p = 1000N / 19,6cm² = 51 N/cm² = 5,1 bar."
    },
    {
      "c": "Beräkningar",
      "t": "Cylinderdata – standardstorlekar",
      "d": "Ø8: A₁=0,5cm², Ø12: 1,13cm², Ø20: 3,14cm², Ø32: 8,04cm², Ø50: 19,6cm², Ø80: 50cm², Ø125: 122cm², Ø200: 314cm²."
    },
    {
      "c": "Beräkningar",
      "t": "Enhetsomvandling – kraft och tryck",
      "d": "1 bar × 1 cm² = 10 N. 1 MPa = 10 bar. 1 N/mm² = 10 bar. 1 kgf ≈ 9,81 N ≈ 10 N (approximation)."
    }
  ],
  "comparison": "<div class=\"slabel\" style=\"margin-top:0;\">Sensorjämförelse</div>\n<div class=\"comp-grid\">\n<div class=\"comp-card\"><div class=\"comp-h\"><span class=\"tag\" style=\"background:#4f46e5;color:white\">Magnetkolvsavkännare</span></div>\n<div class=\"comp-r\">Kolvens läge i cylinder</div>\n<div class=\"comp-r\">Permanentmagnet i kolven</div>\n<div class=\"comp-r\">Binär signal (TILL/FRÅN)</div>\n<div class=\"comp-r\">Enbart på pneumatiska cylindrar</div></div>\n<div class=\"comp-card\"><div class=\"comp-h\"><span class=\"tag\" style=\"background:#7c3aed;color:white\">Induktiv sensor</span></div>\n<div class=\"comp-r\">Metallföremål, kontaktfri</div>\n<div class=\"comp-r\">Magnetfält + virvelströmmar</div>\n<div class=\"comp-r\">Bäst på järn/stål · Al: 0,4×Kn</div>\n<div class=\"comp-r\">Binär, analog variant finns</div></div>\n<div class=\"comp-card\"><div class=\"comp-h\"><span class=\"tag\" style=\"background:#059669;color:white\">Kapacitiv sensor</span></div>\n<div class=\"comp-r\">Alla material inkl. plast/vätska</div>\n<div class=\"comp-r\">Elektriskt fält, kapacitans</div>\n<div class=\"comp-r\">Binär, analog variant finns</div>\n<div class=\"comp-r\">Känslig för smuts och fukt</div></div>\n<div class=\"comp-card\"><div class=\"comp-h\"><span class=\"tag\" style=\"background:#d97706;color:white\">Optisk sensor</span></div>\n<div class=\"comp-r\">Alla material via ljusstråle</div>\n<div class=\"comp-r\">Envägs · Reflex · Direkt · Bakgr.dämpn.</div>\n<div class=\"comp-r\">Binär, analog variant finns</div>\n<div class=\"comp-r\">Känslig för smuts på linsen</div></div>\n</div>\n\n<div class=\"slabel\">Cylinderberäkningar – formelblad</div>\n<table class=\"ptable\"><thead><tr><th>Storhet</th><th>Formel</th><th>Enhet</th><th>Notering</th></tr></thead><tbody>\n<tr><td>Kolvarean A</td><td>π × d²/4</td><td>cm²</td><td>d i cm · 1 bar×cm²=10 N</td></tr>\n<tr><td>Tryckkraft F_teor</td><td>p × A₁</td><td>N</td><td>A₁ = hela kolvytan</td></tr>\n<tr><td>Dragkraft F_teor</td><td>p × A₂</td><td>N</td><td>A₂ = A₁ − stångarea</td></tr>\n<tr><td>Verklig kraft</td><td>F_teor × 0,70</td><td>N</td><td>30% förlust (frikt. 5% + accel. 25%)</td></tr>\n<tr><td>Slagvolym V_T</td><td>A₁ × s</td><td>cm³</td><td>s i cm</td></tr>\n<tr><td>Slagvolym V_D</td><td>A₂ × s</td><td>cm³</td><td>s i cm</td></tr>\n<tr><td>Luftförbrukn. Q</td><td>(V_T+V_D)×(p+1)/1</td><td>Nl/slag</td><td>cm³÷1000=Nl</td></tr>\n<tr><td>Erforderligt tryck</td><td>F / A</td><td>bar</td><td>N÷cm²÷10=bar</td></tr>\n</tbody></table>\n\n<div class=\"slabel\">Ventiltyper – översikt</div>\n<div class=\"comp-grid\">\n<div class=\"comp-card\"><div class=\"comp-h\"><span class=\"tag\" style=\"background:#2563eb;color:white\">5/2-ventil</span></div>\n<div class=\"comp-r\">5 portar, 2 lägen</div>\n<div class=\"comp-r\">Dubbelverkande cylindrar</div>\n<div class=\"comp-r\">1 tryck · 2 arbete · 2 avgaser</div>\n<div class=\"comp-r\">Effektventil – stora flöden</div></div>\n<div class=\"comp-card\"><div class=\"comp-h\"><span class=\"tag\" style=\"background:#7c3aed;color:white\">3/2-ventil</span></div>\n<div class=\"comp-r\">3 portar, 2 lägen</div>\n<div class=\"comp-r\">Enkelverkande cylindrar, signalgivning</div>\n<div class=\"comp-r\">NC (normalt stängd) eller NO</div>\n<div class=\"comp-r\">Signal/logik – litet flöde</div></div>\n<div class=\"comp-card\"><div class=\"comp-h\"><span class=\"tag\" style=\"background:#059669;color:white\">Strypbackventil</span></div>\n<div class=\"comp-r\">Stryper + backfunktion</div>\n<div class=\"comp-r\">Hastighetsstyrning av cylinder</div>\n<div class=\"comp-r\">En riktning strypt, andra fri</div>\n<div class=\"comp-r\">Justerbar strypning</div></div>\n<div class=\"comp-card\"><div class=\"comp-h\"><span class=\"tag\" style=\"background:#d97706;color:white\">Tryckregulator</span></div>\n<div class=\"comp-r\">Konstant drifttryck</div>\n<div class=\"comp-r\">Ingår i FRL-enhet</div>\n<div class=\"comp-r\">Filter–Regulator–Smörjare</div>\n<div class=\"comp-r\">Skyddar anläggning mot tryckvariationer</div></div>\n</div>\n\n<div class=\"slabel\">PLC-val – checklista</div>\n<table class=\"ptable\"><thead><tr><th>Parameter</th><th>Vad du behöver veta</th></tr></thead><tbody>\n<tr><td>Antal I/O</td><td>Räkna sensorer (ingångar) + ställdon (utgångar). Lägg till 20% marginal för expansion.</td></tr>\n<tr><td>Signaltyper</td><td>Digitalt (24VDC) eller analogt (4–20mA, 0–10V)? Kontrollera varje sensor och ställdon.</td></tr>\n<tr><td>Kommunikation</td><td>Fältbuss (PROFIBUS, Profinet, EtherNet/IP) eller konventionell parallell kabeldragning?</td></tr>\n<tr><td>Kraftkälla</td><td>Intern (PLC matar ut 24V) eller extern (separat strömförsörjning för utgångar)?</td></tr>\n<tr><td>Svarstid</td><td>Tidskritiska applikationer kräver kort scantid. Standard PLC: 1–10 ms/1000 instruktioner.</td></tr>\n<tr><td>Programkapacitet</td><td>Antal instruktioner, minnesstorlek. Litet PLC: ~800 instruktioner lagrade.</td></tr>\n</tbody></table>\n\n<div class=\"slabel\">Cylinderdata – standardstorlekar</div>\n<table class=\"ptable\"><thead><tr><th>Kolv Ø mm</th><th>Kolvstång Ø mm</th><th>A₁ cm²</th><th>A₂ cm²</th><th>F₁ N/bar</th><th>F₂ N/bar</th></tr></thead><tbody>\n<tr><td>8</td><td>4</td><td>0,50</td><td>0,37</td><td>5</td><td>3,8</td></tr>\n<tr><td>12</td><td>6</td><td>1,13</td><td>0,85</td><td>11,3</td><td>8,5</td></tr>\n<tr><td>16</td><td>6</td><td>2,01</td><td>1,73</td><td>20,1</td><td>17,3</td></tr>\n<tr><td>20</td><td>8</td><td>3,14</td><td>2,64</td><td>31,4</td><td>26,4</td></tr>\n<tr><td>32</td><td>12</td><td>8,04</td><td>6,91</td><td>80,4</td><td>69,1</td></tr>\n<tr><td>50</td><td>18</td><td>19,6</td><td>16,5</td><td>196</td><td>165</td></tr>\n<tr><td>80</td><td>22</td><td>50,3</td><td>46,5</td><td>500</td><td>454</td></tr>\n<tr><td>125</td><td>30</td><td>122</td><td>115</td><td>1220</td><td>1147</td></tr>\n</tbody></table>",
  "srData": {}
}
